{
  "_class": "symbolInstance",
  "booleanOperation": 0,
  "clippingMaskMode": 0,
  "do_objectID": "D469217A-E101-44A5-B3FA-CE33DB91E0F6",
  "exportOptions": {
    "_class": "exportOptions",
    "do_objectID": "3AB42E40-C837-4E86-86B9-827CE4B4D524",
    "exportFormats": [
    ],
    "includedLayerIds": [
    ],
    "layerOptions": 0,
    "shouldTrim": false
  },
  "frame": {
    "_class": "rect",
    "constrainProportions": false,
    "do_objectID": "07226B00-5FC2-4420-87E6-484CF6E75782",
    "height": 288,
    "width": 168,
    "x": 944.0000000000001,
    "y": 717
  },
  "hasClippingMask": false,
  "horizontalSpacing": 0,
  "isFixedToViewport": false,
  "isFlippedHorizontal": false,
  "isFlippedVertical": false,
  "isLocked": false,
  "isVisible": true,
  "layerListExpandedType": 0,
  "name": "Cards / List 2-up / Filled / Body / Resting",
  "nameIsFixed": false,
  "overrideValues": [
  ],
  "resizingConstraint": 63,
  "resizingType": 0,
  "rotation": 0,
  "scale": 1,
  "shouldBreakMaskChain": false,
  "style": {
    "_class": "style",
    "do_objectID": "F25CEE11-B06C-44B7-A585-B1F78ACB4699",
    "endMarkerType": 0,
    "miterLimit": 10,
    "startMarkerType": 0,
    "windingRule": 1
  },
  "symbolID": "043A36F6-B5D5-43E9-8755-BCB687DB1F71",
  "verticalSpacing": 0
}