{
  "_class": "symbolInstance",
  "booleanOperation": 0,
  "clippingMaskMode": 0,
  "do_objectID": "21CF9800-B12C-4DEC-A9EC-4314442381D2",
  "exportOptions": {
    "_class": "exportOptions",
    "do_objectID": "F82193AF-3522-4863-B457-CAD08A9E1543",
    "exportFormats": [
    ],
    "includedLayerIds": [
    ],
    "layerOptions": 0,
    "shouldTrim": false
  },
  "frame": {
    "_class": "rect",
    "constrainProportions": false,
    "do_objectID": "8FA5A1E2-E8F0-4D81-9E1C-94CE4CD236D2",
    "height": 32,
    "width": 141,
    "x": 0,
    "y": 0
  },
  "hasClippingMask": false,
  "horizontalSpacing": 0,
  "isFixedToViewport": false,
  "isFlippedHorizontal": false,
  "isFlippedVertical": false,
  "isLocked": false,
  "isVisible": true,
  "layerListExpandedType": 0,
  "name": "CONTAINER COLOR",
  "nameIsFixed": true,
  "overrideValues": [
  ],
  "resizingConstraint": 47,
  "resizingType": 0,
  "rotation": 0,
  "scale": 1,
  "shouldBreakMaskChain": false,
  "style": {
    "_class": "style",
    "do_objectID": "83A0AE9A-FD8B-4EDD-9A2C-9835678CCF99",
    "endMarkerType": 0,
    "miterLimit": 10,
    "startMarkerType": 0,
    "windingRule": 1
  },
  "symbolID": "13A98AD8-2C72-4ED5-B872-A1CDF9769942",
  "verticalSpacing": 0
}