{
  "_class": "artboard",
  "backgroundColor": {
    "_class": "color",
    "alpha": 1,
    "blue": 1,
    "do_objectID": "CF20DDD4-8E01-4EDE-9166-CED2BACB2344",
    "green": 1,
    "red": 1
  },
  "booleanOperation": 0,
  "clippingMaskMode": 0,
  "do_objectID": "CCF37F71-FC0B-4AC3-808D-8284B06DFA24",
  "exportOptions": {
    "_class": "exportOptions",
    "do_objectID": "F03B8486-3C05-4AD6-B45D-4E2422804AE7",
    "exportFormats": [
      {
        "_class": "exportFormat",
        "absoluteSize": 0,
        "fileFormat": "png",
        "name": "",
        "namingScheme": 0,
        "scale": 1,
        "visibleScaleType": 0
      },
      {
        "_class": "exportFormat",
        "absoluteSize": 0,
        "fileFormat": "png",
        "name": "@2x",
        "namingScheme": 0,
        "scale": 2,
        "visibleScaleType": 0
      },
      {
        "_class": "exportFormat",
        "absoluteSize": 0,
        "do_objectID": "F758E3AC-83BA-4840-84DE-D067C7A64CCC",
        "fileFormat": "svg",
        "name": "",
        "namingScheme": 0,
        "scale": 1,
        "visibleScaleType": 0
      },
      {
        "_class": "exportFormat",
        "absoluteSize": 0,
        "do_objectID": "B55B239E-E945-4C29-B44E-1EDFF141D7F3",
        "fileFormat": "eps",
        "name": "",
        "namingScheme": 0,
        "scale": 1,
        "visibleScaleType": 0
      }
    ],
    "includedLayerIds": [
    ],
    "layerOptions": 0,
    "shouldTrim": false
  },
  "frame": {
    "_class": "rect",
    "constrainProportions": false,
    "do_objectID": "9405F7DC-5784-468D-8396-F5EBA504F8CC",
    "height": 43,
    "width": 187,
    "x": 668,
    "y": -101
  },
  "hasBackgroundColor": false,
  "hasClickThrough": true,
  "hasClippingMask": false,
  "horizontalRulerData": {
    "_class": "rulerData",
    "base": 0,
    "do_objectID": "F8301EC4-DFE5-4742-8830-DB686869CCF6",
    "guides": [
    ]
  },
  "includeBackgroundColorInExport": true,
  "includeInCloudUpload": true,
  "isFixedToViewport": false,
  "isFlippedHorizontal": false,
  "isFlippedVertical": false,
  "isFlowHome": false,
  "isLocked": false,
  "isVisible": true,
  "layerListExpandedType": 2,
  "layers": [
    {
      "class": "group",
      "id": "2E38897E-37C8-4A79-A321-B6FC9355338A"
    },
    {
      "class": "slice",
      "id": "8ED94C39-C193-4020-8494-257793CEFA0A"
    }
  ],
  "name": "btn_google_signin_light_normal_web",
  "nameIsFixed": false,
  "resizesContent": false,
  "resizingConstraint": 63,
  "resizingType": 0,
  "rotation": 0,
  "shouldBreakMaskChain": true,
  "style": {
    "_class": "style",
    "do_objectID": "00DFBE76-DB01-4E10-8D14-0804F7A7FA20",
    "endMarkerType": 0,
    "miterLimit": 10,
    "startMarkerType": 0,
    "windingRule": 1
  },
  "verticalRulerData": {
    "_class": "rulerData",
    "base": 0,
    "do_objectID": "3CD24D4E-9EE9-4341-86B5-F66AD568BE97",
    "guides": [
    ]
  }
}