{
  "_class": "shapePath",
  "booleanOperation": -1,
  "clippingMaskMode": 0,
  "do_objectID": "70C29812-A888-49FF-9CDF-3A26ACD79432",
  "edited": true,
  "exportOptions": {
    "_class": "exportOptions",
    "do_objectID": "390FBED6-0FB3-4842-9308-F56C8835FC61",
    "exportFormats": [
    ],
    "includedLayerIds": [
    ],
    "layerOptions": 0,
    "shouldTrim": false
  },
  "frame": {
    "_class": "rect",
    "constrainProportions": false,
    "height": 80,
    "width": 79.999,
    "x": 56.00250000000233,
    "y": 55.99950000000001
  },
  "hasClippingMask": false,
  "isClosed": true,
  "isFixedToViewport": false,
  "isFlippedHorizontal": false,
  "isFlippedVertical": false,
  "isLocked": false,
  "isVisible": true,
  "layerListExpandedType": 0,
  "name": "Stroke 165",
  "nameIsFixed": false,
  "pointRadiusBehaviour": 1,
  "points": [
    {
      "_class": "curvePoint",
      "cornerRadius": 0,
      "curveFrom": "{0.22387779847248088, 0}",
      "curveMode": 2,
      "curveTo": "{0.7761222015275191, 0}",
      "hasCurveFrom": true,
      "hasCurveTo": true,
      "point": "{0.50000625007812605, 0}"
    },
    {
      "_class": "curvePoint",
      "cornerRadius": 0,
      "curveFrom": "{0, 0.77612500000000006}",
      "curveMode": 2,
      "curveTo": "{0, 0.22385000000000002}",
      "hasCurveFrom": true,
      "hasCurveTo": true,
      "point": "{0, 0.5}"
    },
    {
      "_class": "curvePoint",
      "cornerRadius": 0,
      "curveFrom": "{0.7761222015275191, 1}",
      "curveMode": 2,
      "curveTo": "{0.22387779847248088, 1}",
      "hasCurveFrom": true,
      "hasCurveTo": true,
      "point": "{0.50000625007812605, 1}"
    },
    {
      "_class": "curvePoint",
      "cornerRadius": 0,
      "curveFrom": "{1, 0.22385000000000002}",
      "curveMode": 2,
      "curveTo": "{1, 0.77612500000000006}",
      "hasCurveFrom": true,
      "hasCurveTo": true,
      "point": "{1, 0.5}"
    }
  ],
  "resizingConstraint": 18,
  "resizingType": 0,
  "rotation": 0,
  "shouldBreakMaskChain": true,
  "style": {
    "_class": "style",
    "borders": [
      {
        "_class": "border",
        "color": {
          "_class": "color",
          "alpha": 1,
          "blue": 0,
          "green": 0,
          "red": 0
        },
        "fillType": 0,
        "isEnabled": true,
        "position": 0,
        "thickness": 0.5
      }
    ],
    "do_objectID": "964FF031-62DD-489D-A095-9051304BBE7C",
    "endMarkerType": 0,
    "miterLimit": 10,
    "startMarkerType": 0,
    "windingRule": 1
  }
}